face_mask/__init__.py
face_mask/__main__.py
face_mask/images/black-mask.png
face_mask/images/blue-mask.png
face_mask/images/default-mask.png
face_mask/images/red-mask.png
face_mask-0.3.0.dist-info/LICENSE
face_mask-0.3.0.dist-info/METADATA
face_mask-0.3.0.dist-info/WHEEL
face_mask-0.3.0.dist-info/entry_points.txt
face_mask-0.3.0.dist-info/top_level.txt
face_mask-0.3.0.dist-info/RECORD
